{"usd":{"name":"US Dollar","sell":"54850","buy":"54750"},"eur":{"name":"Euro","sell":"60000","buy":"59900"},"gbp":{"name":"British Pound","sell":"68200","buy":"68000"},"chf":{"name":"Swiss Franc","sell":"61000","buy":"60900"},"cad":{"name":"Canadian Dollar","sell":"40300","buy":"40200"},"aud":{"name":"Australian Dollar","sell":"36650","buy":"36550"},"sek":{"name":"Swedish Krona","sell":"5300","buy":"5285"},"nok":{"name":"Norwegian Krone","sell":"5075","buy":"5060"},"rub":{"name":"Russian Ruble","sell":"685","buy":"680"},"thb":{"name":"Thai Baht","sell":"1605","buy":"1600"},"sgd":{"name":"Singapore Dollar","sell":"41000","buy":"40900"},"hkd":{"name":"Hong Kong Dollar","sell":"6985","buy":"6955"},"azn":{"name":"Azerbaijani Manat","sell":"32200","buy":"32100"},"amd":{"name":"Armenian Dram","sell":"1415","buy":"1410"},"dkk":{"name":"Danish Krone","sell":"8050","buy":"8030"},"aed":{"name":"UAE Dirham","sell":"15200","buy":"15170"},"jpy":{"name":"Japanese Yen","sell":"3990","buy":"3980"},"try":{"name":"Turkish Lira","sell":"2815","buy":"2795"},"cny":{"name":"Chinese Yuan","sell":"7935","buy":"7915"},"sar":{"name":"KSA Riyal","sell":"14600","buy":"14500"},"inr":{"name":"Indian Rupee","sell":"670","buy":"670"},"myr":{"name":"Ringgit","sell":"12300","buy":"12200"},"afn":{"name":"Afghan Afghani","sell":"630","buy":"625"},"kwd":{"name":"Kuwaiti Dinar","sell":"178900","buy":"178500"},"iqd":{"name":"Iraqi Dinar","sell":"4195","buy":"4185"},"bhd":{"name":"Bahraini Dinar","sell":"145450","buy":"144950"},"omr":{"name":"Omani Rial","sell":"142450","buy":"142150"},"qar":{"name":"Qatari Riyal","sell":"15050","buy":"15050"},"gol18":{"name":"Gold Gram","sell":"2722654"},"mithqal":{"name":"Gold Mithqal","sell":"11794000"},"ounce":{"name":"Gold Ounce","sell":"2003.4"}}
