{"usd":{"name":"US Dollar","sell":"39540","buy":"39440"},"eur":{"name":"Euro","sell":"42415","buy":"42265"},"gbp":{"name":"British Pound","sell":"47835","buy":"47635"},"chf":{"name":"Swiss Franc","sell":"42765","buy":"42615"},"cad":{"name":"Canadian Dollar","sell":"29140","buy":"29040"},"aud":{"name":"Australian Dollar","sell":"26905","buy":"26805"},"sek":{"name":"Swedish Krona","sell":"3790","buy":"3775"},"nok":{"name":"Norwegian Krone","sell":"4045","buy":"4030"},"rub":{"name":"Russian Ruble","sell":"535","buy":"530"},"thb":{"name":"Thai Baht","sell":"1145","buy":"1140"},"sgd":{"name":"Singapore Dollar","sell":"29495","buy":"29395"},"hkd":{"name":"Hong Kong Dollar","sell":"5060","buy":"5030"},"azn":{"name":"Azerbaijani Manat","sell":"23205","buy":"23105"},"amd":{"name":"Armenian Dram","sell":"1005","buy":"1000"},"dkk":{"name":"Danish Krone","sell":"5690","buy":"5670"},"aed":{"name":"UAE Dirham","sell":"10765","buy":"10745"},"jpy":{"name":"Japanese Yen","sell":"3015","buy":"3005"},"try":{"name":"Turkish Lira","sell":"2115","buy":"2095"},"cny":{"name":"Chinese Yuan","sell":"5730","buy":"5710"},"sar":{"name":"KSA Riyal","sell":"10520","buy":"10490"},"inr":{"name":"Indian Rupee","sell":"477","buy":"477"},"myr":{"name":"Ringgit","sell":"8975","buy":"8945"},"afn":{"name":"Afghan Afghani","sell":"451","buy":"446"},"kwd":{"name":"Kuwaiti Dinar","sell":"129065","buy":"128665"},"iqd":{"name":"Iraqi Dinar","sell":"2705","buy":"2695"},"bhd":{"name":"Bahraini Dinar","sell":"104995","buy":"104495"},"omr":{"name":"Omani Rial","sell":"102690","buy":"102390"},"qar":{"name":"Qatari Riyal","sell":"10860","buy":"10830"},"gol18":{"name":"Gold Gram","sell":"1772934"},"mithqal":{"name":"Gold Mithqal","sell":"7680000"},"ounce":{"name":"Gold Ounce","sell":"1823.86"}}
