{"usd":{"name":"US Dollar","sell":"39530","buy":"39430"},"eur":{"name":"Euro","sell":"42400","buy":"42250"},"gbp":{"name":"British Pound","sell":"47825","buy":"47625"},"chf":{"name":"Swiss Franc","sell":"42755","buy":"42605"},"cad":{"name":"Canadian Dollar","sell":"29130","buy":"29030"},"aud":{"name":"Australian Dollar","sell":"26900","buy":"26800"},"sek":{"name":"Swedish Krona","sell":"3790","buy":"3775"},"nok":{"name":"Norwegian Krone","sell":"4045","buy":"4030"},"rub":{"name":"Russian Ruble","sell":"535","buy":"530"},"thb":{"name":"Thai Baht","sell":"1145","buy":"1140"},"sgd":{"name":"Singapore Dollar","sell":"29485","buy":"29385"},"hkd":{"name":"Hong Kong Dollar","sell":"5060","buy":"5030"},"azn":{"name":"Azerbaijani Manat","sell":"23200","buy":"23100"},"amd":{"name":"Armenian Dram","sell":"1005","buy":"1000"},"dkk":{"name":"Danish Krone","sell":"5690","buy":"5670"},"aed":{"name":"UAE Dirham","sell":"10765","buy":"10745"},"jpy":{"name":"Japanese Yen","sell":"3015","buy":"3005"},"try":{"name":"Turkish Lira","sell":"2115","buy":"2095"},"cny":{"name":"Chinese Yuan","sell":"5730","buy":"5710"},"sar":{"name":"KSA Riyal","sell":"10515","buy":"10485"},"inr":{"name":"Indian Rupee","sell":"477","buy":"477"},"myr":{"name":"Ringgit","sell":"8975","buy":"8945"},"afn":{"name":"Afghan Afghani","sell":"451","buy":"446"},"kwd":{"name":"Kuwaiti Dinar","sell":"129035","buy":"128635"},"iqd":{"name":"Iraqi Dinar","sell":"2705","buy":"2695"},"bhd":{"name":"Bahraini Dinar","sell":"104970","buy":"104470"},"omr":{"name":"Omani Rial","sell":"102665","buy":"102365"},"qar":{"name":"Qatari Riyal","sell":"10855","buy":"10825"},"gol18":{"name":"Gold Gram","sell":"1782630"},"mithqal":{"name":"Gold Mithqal","sell":"7722000"},"ounce":{"name":"Gold Ounce","sell":"1823.86"}}
