{"usd":{"name":"US Dollar","sell":"51200","buy":"51100"},"eur":{"name":"Euro","sell":"55450","buy":"55350"},"gbp":{"name":"British Pound","sell":"63600","buy":"63400"},"chf":{"name":"Swiss Franc","sell":"57000","buy":"56900"},"cad":{"name":"Canadian Dollar","sell":"37850","buy":"37750"},"aud":{"name":"Australian Dollar","sell":"33950","buy":"33850"},"sek":{"name":"Swedish Krona","sell":"4905","buy":"4890"},"nok":{"name":"Norwegian Krone","sell":"4745","buy":"4730"},"rub":{"name":"Russian Ruble","sell":"635","buy":"630"},"thb":{"name":"Thai Baht","sell":"1495","buy":"1490"},"sgd":{"name":"Singapore Dollar","sell":"38100","buy":"38000"},"hkd":{"name":"Hong Kong Dollar","sell":"6535","buy":"6505"},"azn":{"name":"Azerbaijani Manat","sell":"30100","buy":"30000"},"amd":{"name":"Armenian Dram","sell":"1315","buy":"1310"},"dkk":{"name":"Danish Krone","sell":"7450","buy":"7430"},"aed":{"name":"UAE Dirham","sell":"14250","buy":"14220"},"jpy":{"name":"Japanese Yen","sell":"3735","buy":"3725"},"try":{"name":"Turkish Lira","sell":"2590","buy":"2570"},"cny":{"name":"Chinese Yuan","sell":"7315","buy":"7295"},"sar":{"name":"KSA Riyal","sell":"13650","buy":"13550"},"inr":{"name":"Indian Rupee","sell":"620","buy":"620"},"myr":{"name":"Ringgit","sell":"11300","buy":"11200"},"afn":{"name":"Afghan Afghani","sell":"585","buy":"580"},"kwd":{"name":"Kuwaiti Dinar","sell":"166700","buy":"166300"},"iqd":{"name":"Iraqi Dinar","sell":"3900","buy":"3890"},"bhd":{"name":"Bahraini Dinar","sell":"135800","buy":"135300"},"omr":{"name":"Omani Rial","sell":"133150","buy":"132850"},"qar":{"name":"Qatari Riyal","sell":"14050","buy":"14050"},"gol18":{"name":"Gold Gram","sell":"2519737"},"mithqal":{"name":"Gold Mithqal","sell":"10915000"},"ounce":{"name":"Gold Ounce","sell":"1985.86"}}
