{"usd":{"name":"US Dollar","sell":"52200","buy":"52100"},"eur":{"name":"Euro","sell":"56650","buy":"56550"},"gbp":{"name":"British Pound","sell":"64450","buy":"64250"},"chf":{"name":"Swiss Franc","sell":"56900","buy":"56800"},"cad":{"name":"Canadian Dollar","sell":"38700","buy":"38600"},"aud":{"name":"Australian Dollar","sell":"35050","buy":"34950"},"sek":{"name":"Swedish Krona","sell":"5030","buy":"5015"},"nok":{"name":"Norwegian Krone","sell":"5020","buy":"5005"},"rub":{"name":"Russian Ruble","sell":"670","buy":"665"},"thb":{"name":"Thai Baht","sell":"1515","buy":"1510"},"sgd":{"name":"Singapore Dollar","sell":"39200","buy":"39100"},"hkd":{"name":"Hong Kong Dollar","sell":"6650","buy":"6620"},"azn":{"name":"Azerbaijani Manat","sell":"30700","buy":"30600"},"amd":{"name":"Armenian Dram","sell":"1345","buy":"1340"},"dkk":{"name":"Danish Krone","sell":"7600","buy":"7580"},"aed":{"name":"UAE Dirham","sell":"14200","buy":"14200"},"jpy":{"name":"Japanese Yen","sell":"3915","buy":"3905"},"try":{"name":"Turkish Lira","sell":"2720","buy":"2700"},"cny":{"name":"Chinese Yuan","sell":"7580","buy":"7560"},"sar":{"name":"KSA Riyal","sell":"13900","buy":"13800"},"inr":{"name":"Indian Rupee","sell":"635","buy":"635"},"myr":{"name":"Ringgit","sell":"11800","buy":"11700"},"afn":{"name":"Afghan Afghani","sell":"600","buy":"595"},"kwd":{"name":"Kuwaiti Dinar","sell":"170050","buy":"169650"},"iqd":{"name":"Iraqi Dinar","sell":"3575","buy":"3565"},"bhd":{"name":"Bahraini Dinar","sell":"138450","buy":"137950"},"omr":{"name":"Omani Rial","sell":"135600","buy":"135300"},"qar":{"name":"Qatari Riyal","sell":"14350","buy":"14350"},"gol18":{"name":"Gold Gram","sell":"2564752"},"mithqal":{"name":"Gold Mithqal","sell":"11110000"},"ounce":{"name":"Gold Ounce","sell":"1975.66"}}
