{"usd":{"name":"US Dollar","sell":"48900","buy":"48800"},"eur":{"name":"Euro","sell":"51800","buy":"51700"},"gbp":{"name":"British Pound","sell":"58650","buy":"58450"},"chf":{"name":"Swiss Franc","sell":"52700","buy":"52600"},"cad":{"name":"Canadian Dollar","sell":"35350","buy":"35250"},"aud":{"name":"Australian Dollar","sell":"32200","buy":"32100"},"sek":{"name":"Swedish Krona","sell":"4550","buy":"4535"},"nok":{"name":"Norwegian Krone","sell":"4585","buy":"4570"},"rub":{"name":"Russian Ruble","sell":"640","buy":"635"},"thb":{"name":"Thai Baht","sell":"1395","buy":"1390"},"sgd":{"name":"Singapore Dollar","sell":"36100","buy":"36000"},"hkd":{"name":"Hong Kong Dollar","sell":"6230","buy":"6200"},"azn":{"name":"Azerbaijani Manat","sell":"29150","buy":"29050"},"amd":{"name":"Armenian Dram","sell":"1265","buy":"1260"},"dkk":{"name":"Danish Krone","sell":"6955","buy":"6935"},"aed":{"name":"UAE Dirham","sell":"13300","buy":"13300"},"jpy":{"name":"Japanese Yen","sell":"3575","buy":"3565"},"try":{"name":"Turkish Lira","sell":"2580","buy":"2560"},"cny":{"name":"Chinese Yuan","sell":"7035","buy":"7015"},"sar":{"name":"KSA Riyal","sell":"13000","buy":"12900"},"inr":{"name":"Indian Rupee","sell":"595","buy":"595"},"myr":{"name":"Ringgit","sell":"10800","buy":"10700"},"afn":{"name":"Afghan Afghani","sell":"555","buy":"550"},"kwd":{"name":"Kuwaiti Dinar","sell":"159150","buy":"158750"},"iqd":{"name":"Iraqi Dinar","sell":"3355","buy":"3345"},"bhd":{"name":"Bahraini Dinar","sell":"129700","buy":"129200"},"omr":{"name":"Omani Rial","sell":"127000","buy":"126700"},"qar":{"name":"Qatari Riyal","sell":"13450","buy":"13450"},"gol18":{"name":"Gold Gram","sell":"2203471"},"mithqal":{"name":"Gold Mithqal","sell":"9545000"},"ounce":{"name":"Gold Ounce","sell":"1835.16"}}
