{"usd":{"name":"US Dollar","sell":"44210","buy":"44110"},"eur":{"name":"Euro","sell":"48275","buy":"48125"},"gbp":{"name":"British Pound","sell":"54860","buy":"54660"},"chf":{"name":"Swiss Franc","sell":"48200","buy":"48050"},"cad":{"name":"Canadian Dollar","sell":"33015","buy":"32915"},"aud":{"name":"Australian Dollar","sell":"31470","buy":"31370"},"sek":{"name":"Swedish Krona","sell":"4330","buy":"4315"},"nok":{"name":"Norwegian Krone","sell":"4475","buy":"4460"},"rub":{"name":"Russian Ruble","sell":"635","buy":"630"},"thb":{"name":"Thai Baht","sell":"1355","buy":"1350"},"sgd":{"name":"Singapore Dollar","sell":"33730","buy":"33630"},"hkd":{"name":"Hong Kong Dollar","sell":"5645","buy":"5615"},"azn":{"name":"Azerbaijani Manat","sell":"25980","buy":"25880"},"amd":{"name":"Armenian Dram","sell":"1125","buy":"1120"},"dkk":{"name":"Danish Krone","sell":"6490","buy":"6470"},"aed":{"name":"UAE Dirham","sell":"12035","buy":"12015"},"jpy":{"name":"Japanese Yen","sell":"3415","buy":"3405"},"try":{"name":"Turkish Lira","sell":"2350","buy":"2330"},"cny":{"name":"Chinese Yuan","sell":"6515","buy":"6495"},"sar":{"name":"KSA Riyal","sell":"11775","buy":"11745"},"inr":{"name":"Indian Rupee","sell":"545","buy":"545"},"myr":{"name":"Ringgit","sell":"10415","buy":"10385"},"afn":{"name":"Afghan Afghani","sell":"499","buy":"494"},"kwd":{"name":"Kuwaiti Dinar","sell":"144925","buy":"144525"},"iqd":{"name":"Iraqi Dinar","sell":"3045","buy":"3035"},"bhd":{"name":"Bahraini Dinar","sell":"117275","buy":"116775"},"omr":{"name":"Omani Rial","sell":"114980","buy":"114680"},"qar":{"name":"Qatari Riyal","sell":"12140","buy":"12110"},"gol18":{"name":"Gold Gram","sell":"2107668"},"mithqal":{"name":"Gold Mithqal","sell":"9130000"},"ounce":{"name":"Gold Ounce","sell":"1944.14"}}
