{"usd":{"name":"US Dollar","sell":"44950","buy":"44850"},"eur":{"name":"Euro","sell":"48895","buy":"48745"},"gbp":{"name":"British Pound","sell":"55690","buy":"55490"},"chf":{"name":"Swiss Franc","sell":"48860","buy":"48710"},"cad":{"name":"Canadian Dollar","sell":"33560","buy":"33460"},"aud":{"name":"Australian Dollar","sell":"31295","buy":"31195"},"sek":{"name":"Swedish Krona","sell":"4365","buy":"4350"},"nok":{"name":"Norwegian Krone","sell":"4590","buy":"4575"},"rub":{"name":"Russian Ruble","sell":"660","buy":"655"},"thb":{"name":"Thai Baht","sell":"1375","buy":"1370"},"sgd":{"name":"Singapore Dollar","sell":"34060","buy":"33960"},"hkd":{"name":"Hong Kong Dollar","sell":"5735","buy":"5705"},"azn":{"name":"Azerbaijani Manat","sell":"26380","buy":"26280"},"amd":{"name":"Armenian Dram","sell":"1135","buy":"1130"},"dkk":{"name":"Danish Krone","sell":"6560","buy":"6540"},"aed":{"name":"UAE Dirham","sell":"12235","buy":"12215"},"jpy":{"name":"Japanese Yen","sell":"3470","buy":"3460"},"try":{"name":"Turkish Lira","sell":"2395","buy":"2375"},"cny":{"name":"Chinese Yuan","sell":"6625","buy":"6605"},"sar":{"name":"KSA Riyal","sell":"11975","buy":"11945"},"inr":{"name":"Indian Rupee","sell":"555","buy":"555"},"myr":{"name":"Ringgit","sell":"10490","buy":"10460"},"afn":{"name":"Afghan Afghani","sell":"505","buy":"500"},"kwd":{"name":"Kuwaiti Dinar","sell":"147095","buy":"146695"},"iqd":{"name":"Iraqi Dinar","sell":"3080","buy":"3070"},"bhd":{"name":"Bahraini Dinar","sell":"119250","buy":"118750"},"omr":{"name":"Omani Rial","sell":"116755","buy":"116455"},"qar":{"name":"Qatari Riyal","sell":"12345","buy":"12315"},"gol18":{"name":"Gold Gram","sell":"2108822"},"mithqal":{"name":"Gold Mithqal","sell":"9135000"},"ounce":{"name":"Gold Ounce","sell":"1926.08"}}
